{
  "uid" : "5415e2381b2fe828",
  "name" : "TestGetVehicle.test_others[getVehicleInfo.do-{\"vin\":\"LSGGA54Y6CH224814\",\"userId\":36896812,\"queryType\":1}-{\"code\":0,\"data\":{\"vehicleBrandName\":\"\\u4e0a\\u6d77\\u901a\\u7528\\u522b\\u514b\",\"vehicleColorList\":[],\"vehicleModelName\":\"2012\\u6b3e\\u65b0\\u541b\\u5a012.0L\"},\"msg\":\"\\u6210\\u529f\"}]",
  "title" : "Test others [getVehicleInfo.do-{\"vin\":\"LSGGA54Y6CH224814\",\"userId\":36896812,\"queryType\":1}-{\"code\":0,\"data\":{\"vehicleBrandName\":\"\\u4e0a\\u6d77\\u901a\\u7528\\u522b\\u514b\",\"vehicleColorList\":[],\"vehicleModelName\":\"2012\\u6b3e\\u65b0\\u541b\\u5a012.0L\"},\"msg\":\"\\u6210\\u529f\"}]",
  "time" : {
    "start" : 1502859587349,
    "stop" : 1502859587413,
    "duration" : 64
  },
  "summary" : {
    "attachments" : 0,
    "steps" : 2
  },
  "failure" : {
    "message" : "AssertionError: assert False\n +  where False = compare('{\"code\":11006,\"data\":\"\",\"msg\":\"用户未登陆\"}', '{\"code\":0,\"data\":{\"vehicleBrandName\":\"上海通用别克\",\"vehicleColorList\":[],\"vehicleModelName\":\"2012款新君威2.0L\"},\"msg\":\"成功\"}')",
    "stackTrace" : "self = <test_onLogin.TestGetVehicle object at 0x00000299F9872BE0>\nurl = 'getVehicleInfo.do'\nparam = '{\"vin\":\"LSGGA54Y6CH224814\",\"userId\":36896812,\"queryType\":1}'\nexpected = '{\"code\":0,\"data\":{\"vehicleBrandName\":\"上海通用别克\",\"vehicleColorList\":[],\"vehicleModelName\":\"2012款新君威2.0L\"},\"msg\":\"成功\"}'\n\n    @pytest.mark.parametrize(\"url,param,expected\", general_case(\"查询车辆\", data))\n    @allure.feature('查询车辆测试')\n    def test_others(self, url, param, expected):\n        newPara = general_arg(constArg, eval(param))\n        r = sendRequest(newPara, (path + url).strip())\n>       assert compare(r[0], expected)\nE       assert False\nE        +  where False = compare('{\"code\":11006,\"data\":\"\",\"msg\":\"用户未登陆\"}', '{\"code\":0,\"data\":{\"vehicleBrandName\":\"上海通用别克\",\"vehicleColorList\":[],\"vehicleModelName\":\"2012款新君威2.0L\"},\"msg\":\"成功\"}')\n\ntest_onLogin.py:50: AssertionError"
  },
  "description" : null,
  "severity" : "NORMAL",
  "status" : "FAILED",
  "suite" : {
    "uid" : "3077e459d1dd60d6",
    "name" : "test_onLogin",
    "title" : "Test on login"
  },
  "steps" : [ {
    "name" : "生成参数",
    "title" : "生成参数",
    "time" : {
      "start" : 1502859587350,
      "stop" : 1502859587350,
      "duration" : 0
    },
    "summary" : {
      "attachments" : 0,
      "steps" : 0
    },
    "status" : "PASSED",
    "attachments" : [ ],
    "steps" : [ ]
  }, {
    "name" : "对比结果",
    "title" : "对比结果",
    "time" : {
      "start" : 1502859587410,
      "stop" : 1502859587410,
      "duration" : 0
    },
    "summary" : {
      "attachments" : 0,
      "steps" : 0
    },
    "status" : "PASSED",
    "attachments" : [ ],
    "steps" : [ ]
  } ],
  "attachments" : [ ],
  "issues" : [ ],
  "testIds" : [ {
    "name" : "查询车辆",
    "url" : "查询车辆"
  } ],
  "labels" : [ {
    "name" : "suite-name",
    "value" : "test_onLogin"
  }, {
    "name" : "suite-title",
    "value" : null
  }, {
    "name" : "host",
    "value" : "DESKTOP-QF1GK4S"
  }, {
    "name" : "testId",
    "value" : "查询车辆"
  }, {
    "name" : "feature",
    "value" : "查询车辆测试"
  }, {
    "name" : "severity",
    "value" : "normal"
  }, {
    "name" : "thread",
    "value" : "25692-MainThread"
  } ],
  "parameters" : [ ]
}