{
  "uid" : "d69b1ed2cba04f62",
  "name" : "Testlogin.test_onLogin[param1-expected1]",
  "title" : "Test on login [param1-expected1]",
  "time" : {
    "start" : 1502437975983,
    "stop" : 1502437976017,
    "duration" : 34
  },
  "summary" : {
    "attachments" : 0,
    "steps" : 0
  },
  "failure" : {
    "message" : "TypeError: byte indices must be integers or slices, not str",
    "stackTrace" : "self = <test_onLogin.Testlogin object at 0x000001BF9FD0DBE0>\nparam = {'account': '13701837591', 'password': 'd41d8cd98f00b204e9800998ecf8427e'}\nexpected = {'code': 11004}\n\n    @pytest.mark.parametrize(\"param,expected\",login_data)\n    def test_onLogin(self,param,expected):\n        newPara=dict(constArg,**param)\n        newPara[\"sign\"]=get_sign(newPara)\n        r = sendRequest(newPara,(path+url).strip())\n        result=r[0]\n>       assert result[\"code\"]==expected[\"code\"]\nE       TypeError: byte indices must be integers or slices, not str\n\ntest_onLogin.py:25: TypeError"
  },
  "description" : null,
  "severity" : "NORMAL",
  "status" : "FAILED",
  "suite" : {
    "uid" : "e16f4200b47fdd3b",
    "name" : "test_onLogin",
    "title" : "Test on login"
  },
  "steps" : [ ],
  "attachments" : [ ],
  "issues" : [ ],
  "testIds" : [ ],
  "labels" : [ {
    "name" : "suite-name",
    "value" : "test_onLogin"
  }, {
    "name" : "thread",
    "value" : "2456-MainThread"
  }, {
    "name" : "suite-title",
    "value" : null
  }, {
    "name" : "host",
    "value" : "DESKTOP-QF1GK4S"
  }, {
    "name" : "severity",
    "value" : "normal"
  } ],
  "parameters" : [ ]
}